Metadata-Version: 1.0
Name: AlishaProb
Version: 0.1
Summary: Gaussian and Binomial distributions
Home-page: UNKNOWN
Author: Alisha Gupta
Author-email: guptaalisha0198@gmail.com
License: UNKNOWN
Platform: UNKNOWN
